{
  "name": "ASHOKLEY",
  "current_price": 197.5,
  "open": 188.84,
  "high": 204.55,
  "low": 177.93,
  "change": 8.66,
  "change_pct": 4.59,
  "date": "02-02-2026 to 30-01-2026",
  "updated_time": "04:45 PM",
  "ema": {
    "ema_9": 196.32,
    "ema_20": 195.78,
    "ema_200": 191.5
  },
  "trend": {
    "overall": "Bullish",
    "signal": "BUY",
    "short_term": "Bullish",
    "medium_term": "Bullish",
    "long_term": "Bullish"
  },
  "support_resistance": {
    "resistance": 198.33,
    "support": 177.93,
    "distance_to_resistance": 0.83,
    "distance_to_support": 19.57
  },
  "historical": {
    "dates": [
      "16-01-2026",
      "19-01-2026",
      "20-01-2026",
      "21-01-2026",
      "22-01-2026",
      "23-01-2026",
      "27-01-2026",
      "28-01-2026",
      "29-01-2026",
      "30-01-2026"
    ],
    "prices": [
      184.0,
      188.2,
      180.63,
      181.35,
      191.34,
      192.99,
      193.25,
      195.33,
      193.68,
      197.5
    ]
  },
  "intraday": [
    {
      "time": "09:15",
      "price": 188.84
    },
    {
      "time": "15:30",
      "price": 197.5
    }
  ],
  "shadows": {
    "green_shadow": 7.05,
    "red_shadow": 10.91
  },
  "key_levels": {
    "day_high": 204.55,
    "day_high_time": "15:30",
    "day_low": 177.93,
    "day_low_time": "09:15"
  }
}